normalized_django_settings/__init__.py
normalized_django_settings/__main__.py
normalized_django_settings/_tempfile.py
normalized_django_settings/settings.py
normalized_django_settings-1.1.0.dist-info/licenses/LICENSE
normalized_django_settings-1.1.0.dist-info/METADATA
normalized_django_settings-1.1.0.dist-info/WHEEL
normalized_django_settings-1.1.0.dist-info/top_level.txt
normalized_django_settings-1.1.0.dist-info/RECORD
